{
  "version": "4.5.12",
  "flags": {},
  "shapes": [
    {
      "label": "1",
      "points": [
        [
          292.927536231884,
          254.1014492753623
        ],
        [
          292.927536231884,
          301.2028985507246
        ],
        [
          453.7971014492753,
          298.30434782608694
        ],
        [
          455.2463768115942,
          251.20289855072463
        ]
      ],
      "group_id": null,
      "shape_type": "polygon",
      "flags": {}
    }
  ],
  "imagePath": "../../../Downloads/20220506/B3_3118-辽AD25670.jpg",
  "imageData": null,
  "imageHeight": 638,
  "imageWidth": 642
}