{
  "version": "4.5.12",
  "flags": {},
  "shapes": [
    {
      "label": "1",
      "points": [
        [
          441.41379310344837,
          873.4827586206898
        ],
        [
          439.68965517241384,
          990.7241379310345
        ],
        [
          796.5862068965517,
          1023.4827586206898
        ],
        [
          808.6551724137931,
          911.4137931034484
        ]
      ],
      "group_id": null,
      "shape_type": "polygon",
      "flags": {}
    }
  ],
  "imagePath": "../../dd/WechatIMG73.jpeg",
  "imageData": null,
  "imageHeight": 1702,
  "imageWidth": 1276
}