{
  "version": "4.5.12",
  "flags": {},
  "shapes": [
    {
      "label": "1",
      "points": [
        [
          293.6386554621849,
          526.0420168067227
        ],
        [
          292.7983193277311,
          574.781512605042
        ],
        [
          476.83193277310926,
          579.8235294117648
        ],
        [
          481.87394957983196,
          528.5630252100841
        ]
      ],
      "group_id": null,
      "shape_type": "polygon",
      "flags": {}
    }
  ],
  "imagePath": "../../../Downloads/20220507/地下一层_D1-169-鲁AN236N.jpg",
  "imageData": null,
  "imageHeight": 682,
  "imageWidth": 743
}