{
  "version": "4.5.12",
  "flags": {},
  "shapes": [
    {
      "label": "1",
      "points": [
        [
          190.85714285714286,
          245.0
        ],
        [
          191.42857142857142,
          278.14285714285717
        ],
        [
          290.2857142857143,
          275.85714285714283
        ],
        [
          292.0,
          243.28571428571428
        ]
      ],
      "group_id": null,
      "shape_type": "polygon",
      "flags": {}
    }
  ],
  "imagePath": "../../../Downloads/20220507/地下一层_A1-002-鲁AP3V71.jpg",
  "imageData": null,
  "imageHeight": 540,
  "imageWidth": 509
}