{
  "version": "4.5.12",
  "flags": {},
  "shapes": [
    {
      "label": "1",
      "points": [
        [
          276.71232876712327,
          278.13698630136986
        ],
        [
          276.71232876712327,
          328.13698630136986
        ],
        [
          450.68493150684935,
          333.6164383561644
        ],
        [
          452.7397260273973,
          285.67123287671234
        ]
      ],
      "group_id": null,
      "shape_type": "polygon",
      "flags": {}
    }
  ],
  "imagePath": "../../../Downloads/20220506/B4_559-粤ADP1088.jpg",
  "imageData": null,
  "imageHeight": 579,
  "imageWidth": 610
}