{
  "version": "4.5.12",
  "flags": {},
  "shapes": [
    {
      "label": "1",
      "points": [
        [
          318.2307692307692,
          343.2307692307692
        ],
        [
          311.3076923076923,
          387.8461538461538
        ],
        [
          449.0,
          372.46153846153845
        ],
        [
          452.07692307692304,
          329.38461538461536
        ]
      ],
      "group_id": null,
      "shape_type": "polygon",
      "flags": {}
    }
  ],
  "imagePath": "../../../../../Downloads/20220510/b1_1667-粤E43F98.jpg",
  "imageData": null,
  "imageHeight": 656,
  "imageWidth": 684
}